backbone/__init__.py
backbone/__main__.py
backbone/asyncio/__init__.py
backbone/asyncio/_decorators.py
backbone/asyncio/_origin.py
backbone/asyncio/_security.py
backbone/asyncio/_utils.py
backbone/asyncio/entry.py
backbone/asyncio/namespace.py
backbone/asyncio/stream.py
backbone/asyncio/user.py
backbone/asyncio/workspace.py
backbone/cli/__init__.py
backbone/cli/_config.py
backbone/cli/_format.py
backbone/cli/_models.py
backbone/cli/_utilities.py
backbone/cli/entry.py
backbone/cli/namespace.py
backbone/cli/state.py
backbone/cli/stream.py
backbone/cli/user.py
backbone/cli/workspace.py
backbone/common/cord/__init__.py
backbone/common/cord/_exceptions.py
backbone/common/cord/exceptions.py
backbone/common/cord/fields.py
backbone/common/cord/records.py
backbone/common/cord/validators.py
backbone/common/cord/variants.py
backbone/common/enums.py
backbone/common/exceptions.py
backbone/common/keyspace.py
backbone/common/models/__init__.py
backbone/common/models/_containers.py
backbone/common/models/_exceptions.py
backbone/common/models/entry.py
backbone/common/models/entry_chain.py
backbone/common/models/entry_grant.py
backbone/common/models/namespace.py
backbone/common/models/namespace_chain.py
backbone/common/models/namespace_grant.py
backbone/common/models/stream.py
backbone/common/models/user.py
backbone/common/models/workspace.py
backbone/common/models/workspace_grant.py
backbone/common/protocol/__init__.py
backbone/common/protocol/_factories.py
backbone/common/protocol/entry.py
backbone/common/protocol/namespace.py
backbone/common/protocol/service.py
backbone/common/protocol/stream.py
backbone/common/protocol/user.py
backbone/common/protocol/workspace.py
backbone/common/service.py
backbone/sync/__init__.py
backbone/sync/_decorators.py
backbone/sync/_origin.py
backbone/sync/_security.py
backbone/sync/_utils.py
backbone/sync/entry.py
backbone/sync/namespace.py
backbone/sync/stream.py
backbone/sync/user.py
backbone/sync/workspace.py
backbone-0.6.0.dist-info/entry_points.txt
backbone-0.6.0.dist-info/LICENSE.txt
backbone-0.6.0.dist-info/WHEEL
backbone-0.6.0.dist-info/METADATA
backbone-0.6.0.dist-info/RECORD
