Metadata-Version: 2.1
Name: backbone
Version: 0.6.0
Summary: Tools for development with Backbone
Home-page: https://backbone.dev
License: BSL 1.1
Keywords: security,end-to-end-encryption,E2EE
Author: Backbone Founders
Author-email: root@backbone.dev
Requires-Python: >=3.7,<4.0
Classifier: Development Status :: 3 - Alpha
Classifier: Intended Audience :: Developers
Classifier: License :: Other/Proprietary License
Classifier: Programming Language :: Python :: 3
Classifier: Programming Language :: Python :: 3.10
Classifier: Programming Language :: Python :: 3.7
Classifier: Programming Language :: Python :: 3.8
Classifier: Programming Language :: Python :: 3.9
Classifier: Topic :: Security
Classifier: Topic :: Security :: Cryptography
Classifier: Topic :: Software Development :: Libraries :: Application Frameworks
Classifier: Topic :: Software Development :: Libraries :: Python Modules
Requires-Dist: PyNaCl (>=1.4.0,<2.0.0)
Requires-Dist: halo (>=0.0.31,<0.0.32)
Requires-Dist: httpx (>=0.21.1,<0.22.0)
Requires-Dist: typer (>=0.4.0,<0.5.0)
Requires-Dist: zxcvbn (>=4.4.28,<5.0.0)
Project-URL: Documentation, https://backbone.dev/docs
Project-URL: Repository, https://github.com/backbone-hq/backbone-python
